LICENSE
MANIFEST.in
README.rst
requirements-dev.txt
requirements.txt
setup.py
geokey/__init__.py
geokey/context_processors.py
geokey/version.py
geokey.egg-info/PKG-INFO
geokey.egg-info/SOURCES.txt
geokey.egg-info/dependency_links.txt
geokey.egg-info/requires.txt
geokey.egg-info/top_level.txt
geokey/applications/__init__.py
geokey/applications/base.py
geokey/applications/forms.py
geokey/applications/managers.py
geokey/applications/models.py
geokey/applications/views.py
geokey/applications/migrations/0001_initial.py
geokey/applications/migrations/0002_auto_20150112_1700.py
geokey/applications/migrations/0002_auto_20150112_1807.py
geokey/applications/migrations/0003_auto_20171024_1400.py
geokey/applications/migrations/__init__.py
geokey/applications/tests/__init__.py
geokey/applications/tests/model_factories.py
geokey/applications/tests/test_managers.py
geokey/applications/tests/test_models.py
geokey/applications/tests/test_views.py
geokey/categories/__init__.py
geokey/categories/base.py
geokey/categories/forms.py
geokey/categories/managers.py
geokey/categories/mixins.py
geokey/categories/models.py
geokey/categories/serializers.py
geokey/categories/views.py
geokey/categories/migrations/0001_initial.py
geokey/categories/migrations/0002_auto_20150106_1338.py
geokey/categories/migrations/0003_datefield.py
geokey/categories/migrations/0004_timefield.py
geokey/categories/migrations/0005_auto_20150112_1731.py
geokey/categories/migrations/0006_category_display_field.py
geokey/categories/migrations/0007_auto_20150130_1155.py
geokey/categories/migrations/0008_auto_20150130_1216.py
geokey/categories/migrations/0010_auto_20150202_1023.py
geokey/categories/migrations/0011_auto_20150220_1413.py
geokey/categories/migrations/0012_auto_20150223_1311.py
geokey/categories/migrations/0013_auto_20150130_1440.py
geokey/categories/migrations/0014_auto_20160104_1409.py
geokey/categories/migrations/0015_lookupvalue_symbol.py
geokey/categories/migrations/0016_multiplelookupvalue_symbol.py
geokey/categories/migrations/0017_category_expiry_field.py
geokey/categories/migrations/0018_historicalcategory.py
