Metadata-Version: 1.1
Name: geokey
Version: 1.11.2
Summary: Platform for participatory mapping
Home-page: http://geokey.org.uk
Author: ExCiteS
Author-email: excites@ucl.ac.uk
License: Apache 2.0
Download-URL: https://github.com/ExCiteS/geokey/tarball/1.11.2
Platform: UNKNOWN
